transdoc_python/__init__.py
transdoc_python/__visitor.py
transdoc_python/py.typed
transdoc_python-0.1.4.dist-info/LICENSE
transdoc_python-0.1.4.dist-info/METADATA
transdoc_python-0.1.4.dist-info/WHEEL
transdoc_python-0.1.4.dist-info/entry_points.txt
transdoc_python-0.1.4.dist-info/RECORD
