Metadata-Version: 2.3
Name: transdoc-python
Version: 0.1.4
Summary: A Transdoc handler for Python docstrings
License: MIT
Author: Maddy Guthridge
Author-email: hello@maddyguthridge.com
Requires-Python: >=3.11
Classifier: License :: OSI Approved :: MIT License
Classifier: Programming Language :: Python :: 3
Classifier: Programming Language :: Python :: 3.11
Classifier: Programming Language :: Python :: 3.12
Classifier: Programming Language :: Python :: 3.13
Requires-Dist: libcst (>=1.6.0,<2.0.0)
Requires-Dist: transdoc (>=1.0.0,<2.0.0)
Project-URL: Bug Tracker, https://github.com/MaddyGuthridge/transdoc-python/issues
Project-URL: Documentation, https://maddyguthridge.github.io/transdoc/handlers
Project-URL: Homepage, https://maddyguthridge.github.io/transdoc/handlers
Project-URL: Repository, https://github.com/MaddyGuthridge/transdoc-python
